tracardi_redshift_connector/redshift_connector_action.py
tracardi_redshift_connector-0.1.1.dist-info/LICENSE.md
tracardi_redshift_connector-0.1.1.dist-info/METADATA
tracardi_redshift_connector-0.1.1.dist-info/WHEEL
tracardi_redshift_connector-0.1.1.dist-info/top_level.txt
tracardi_redshift_connector-0.1.1.dist-info/RECORD
